env/bin/rst2html.py
env/bin/rst2html4.py
env/bin/rst2html5.py
env/bin/rst2latex.py
env/bin/rst2man.py
env/bin/rst2odt.py
env/bin/rst2odt_prepstyles.py
env/bin/rst2pseudoxml.py
env/bin/rst2s5.py
env/bin/rst2xetex.py
env/bin/rst2xml.py
env/bin/rstpep2html.py
examples/collect_data.py
examples/count_cve_entries_per_ecosystem.py
examples/load_and_count_cve_entries_with_fix_url.py
examples/load_and_count_cve_entries_with_git_fixes.py
examples/load_and_count_cve_entries_with_git_repo.py
osvutils/__init__.py
osvutils/core/__init__.py
osvutils/core/collector.py
osvutils/core/loader.py
osvutils/core/filters/__init__.py
osvutils/core/filters/affected_packages.py
osvutils/core/filters/base.py
osvutils/core/filters/database.py
osvutils/core/filters/loader.py
osvutils/core/filters/references.py
osvutils/types/__init__.py
osvutils/types/affected.py
osvutils/types/alias.py
osvutils/types/ecosystem.py
osvutils/types/event.py
osvutils/types/osv.py
osvutils/types/package.py
osvutils/types/range.py
osvutils/types/reference.py
osvutils/types/severity.py
osvutils/utils/__init__.py
osvutils/utils/misc.py
osvutils/utils/patterns.py
osv_utils-0.3.10.dist-info/LICENSE
osv_utils-0.3.10.dist-info/METADATA
osv_utils-0.3.10.dist-info/WHEEL
osv_utils-0.3.10.dist-info/top_level.txt
osv_utils-0.3.10.dist-info/RECORD
