Metadata-Version: 2.1
Name: osv-utils
Version: 0.3.10
Summary: A package for parsing, representing, and filtering OSV data.
Author-email: Eduard Pinconschi <eduard.pinconschi@tecnico.ulisboa.pt>
License: MIT License
Project-URL: repository, https://github.com/epicosy/osvutils
Project-URL: homepage, https://github.com/epicosy/osvutils
Keywords: package,osv,utils
Classifier: Topic :: Software Development
Classifier: Programming Language :: Python
Classifier: Environment :: Console
Classifier: Intended Audience :: Developers
Requires-Python: >=3.9
License-File: LICENSE
Requires-Dist: tqdm >=4.66.4
Requires-Dist: pydantic >=2.9.2
Requires-Dist: google-cloud-storage >=2.18.2
Requires-Dist: giturlparse >=0.12.0
Requires-Dist: cvss ==3.2
Provides-Extra: test
Requires-Dist: pytest ; extra == 'test'
Requires-Dist: pytest-cov ; extra == 'test'
Requires-Dist: coverage ; extra == 'test'
Requires-Dist: twine >=1.11.0 ; extra == 'test'
Requires-Dist: setuptools >=38.6.0 ; extra == 'test'
Requires-Dist: wheel >=0.31.0 ; extra == 'test'
